Workbook

Sheet Dashboard
F1: Metric | G1: Value | P1: All Tasks | Q1: Assigned Tasks | R1: In Progress | S1: Waiting | T1: Completed Tasks | U1: Cancelled Tasks
F2: Emails Processed by AI | G2: =COUNTA(Emails[Email ID]) -> 32 | P2: =COUNTA(Tasks[Task ID]) -> 21 | Q2: =countif(Tasks[Status], "Assigned") -> 8 | R2: =countif(Tasks[Status], "In Progress") -> 2 | S2: =countif(Tasks[Status], "Waiting") -> 1 | T2: =countif(Tasks[Status], "Completed") -> 9 | U2: =countif(Tasks[Status], "Cancelled") -> 1
F3: Tasks Automatically Created | G3: =CountIF(Emails[Task Required], "Yes") -> 21
F4: Suggested Replies Generated | G4: =COUNTIF(Emails[Suggested Reply],"<>") -> 30 | P4: Email Categories | Q4: Count
F5: Automation Rate | G5: =COUNTIF(Emails[Processing status],"Processed")/COUNTA(Emails[Email ID]) -> 0.96875 | P5: =Settings!A2 -> Customer enquiry | Q5: =CountIf(Emails[Category], P5) -> 7
P6: =Settings!A3 -> Existing customer | Q6: =CountIf(Emails[Category], P6) -> 8
P7: =Settings!A4 -> Invoice | Q7: =CountIf(Emails[Category], P7) -> 4
P8: =Settings!A5 -> Supplier | Q8: =CountIf(Emails[Category], P8) -> 4
P9: =Settings!A6 -> Complaint | Q9: =CountIf(Emails[Category], P9) -> 3
P10: =Settings!A7 -> Spam | Q10: =CountIf(Emails[Category], P10) -> 6
A12: =Settings!A8 | D12: Total Emails Received | E12: Processed Successfully | F12: Tasks Identified | G12: Spam Filtered | H12: Processing Errors
A13: =Settings!A9 | D13: =COUNTA(Emails[Email ID]) -> 32 | E13: =COUNTIF(Emails[Processing status], "Processed") -> 31 | F13: =COUNTIF(Emails[Task Required], "Yes") -> 21 | G13: =COUNTIF(Emails[Category], "Spam") -> 6 | H13: =COUNTIF(Emails[Processing status], "Error") -> 1
P14: Employee Name | Q14: Current Workload
P15: Jake Marshall | Q15: {=_xlfn.XLOOKUP(P15,Employees[Employee Name],Employees[Current Task Count],"")} -> 3
P16: Donna Rourke | Q16: {=_xlfn.XLOOKUP(P16,Employees[Employee Name],Employees[Current Task Count],"")} -> 1
P17: David Trainer | Q17: {=_xlfn.XLOOKUP(P17,Employees[Employee Name],Employees[Current Task Count],"")} -> 2
P18: Harry Lewis | Q18: {=_xlfn.XLOOKUP(P18,Employees[Employee Name],Employees[Current Task Count],"")} -> 3

Sheet Emails
A1: Email ID | B1: Gmail Message ID | C1: Thread ID | D1: Customer ID | E1: Sender Name | F1: Sender Email | G1: Email Title | H1: Email Body | I1: Received Date | J1: Category | K1: Summary | L1: Priority | M1: Suggested Reply | N1: Task Required | O1: Processing status
A2: EM0002 | B2: 19f9ac56457f16bb | C2: 19f9ac56457f16bb | D2: CST0002 | E2: Darragh Hurley | F2: dazmanchelsea@gmail.com | G2: Need to reschedule an appointment | H2: Hi, We were meant to have a meeting next Monday the 27th of July. Unfortunately I have become very ill and won't be working on Monday. Can we reschedule to some time later in the week? Regards, Darragh | I2: 2026-07-25T19:34:03.000Z | J2: Existing Customer | K2: Darragh Hurley has requested to reschedule the meeting set for Monday, July 27th, due to illness. He has asked to move the appointment to a later date in the same week. | L2: Medium | M2: Hi Darragh, Thank you for reaching out and letting us know. I am very sorry to hear that you are unwell, and I hope you have a speedy recovery. We would be happy to reschedule our meeting to later in the week. Please let us know what days and times work best for you once you are feeling better, and we will get that arranged. Take care and get well soon. Best regards, [Your Name] | N2: Yes | O2: Processed
A3: EM0003 | B3: 19f9acbb3f165e21 | C3: 19f9acbb3f165e21 | D3: CST0003 | E3: Darragh Hurley | F3: darragh.hurley23@gmail.com | G3: Upcoming event | H3: Hi, The email about the event for August 3rd didn't have an option to RSVP. Who should I contact to let them know? Thanks, Darragh | I3: 2026-07-25T19:40:56.000Z | J3: Customer Enquiry | K3: The sender is inquiring about how to RSVP for an upcoming event on August 3rd because the invitation email did not include an RSVP option. | L3: Medium | M3: Hi Darragh, Thank you for reaching out and letting us know. We apologize for the oversight in the invitation email. You can RSVP directly by replying to this email, and I will ensure you are added to the attendee list. Alternatively, you can contact our events team at events@company.com for any further assistance. We hope to see you there! Best regards, [Your Name] [Your Company] | N3: Yes | O3: Processed
A4: EM0004 | B4: 19fa1178ff189dac | C4: 19fa1178ff189dac | D4: CST0004 | E4: Seeking | F4: alerts@account.seeking.com | G4: Check out the newest members in your area! | H4: 96 Hi Peter, here are some new members in your area! Morrigan 39 &#183; Calgary julie 37 &#183; Three Hills Sabrina 31 &#183; Calgary Anita 24 &#183; Calgary Seeking Member 27 &#183; Calgary Seeking Member 33 &#183; Olds Search for More | Do not share any personal information (credit card info, bank account, address, etc.) with anyone under any circumstances. Never disclose your personal banking information, including account numbers or passwords. | | | Unsubscribe | | | © 2005 - 2026 Seeking in conjunction with Reflex Media – All rights reserved. W8Tech Cyprus Limited, IRAKLEOUS 2, FLAT/OFFICE 101 2320 NICOSIA, CYPRUS | | I4: 2026-07-27T01:01:42.000Z | J4: Spam | K4: This is an automated promotional email from Seeking.com showcasing new members in the recipient's area. | L4: No Response Needed | M4: No response is required for this automated marketing email. | N4: No | O4: Processed
A5: EM0005 | B5: 19fb31dcd306373d | C5: 19fb31dcd306373d | D5: CST0004 | E5: Seeking | F5: alerts@account.seeking.com | G5: Check out the newest members in your area! | H5: 96 Hi Peter, here are some new members in your area! julie 37 &#183; Three Hills Sabrina 31 &#183; Calgary Anita 24 &#183; Calgary Seeking Member 27 &#183; Calgary Seeking Member 33 &#183; Olds Kelsie 35 &#183; Red Deer Search for More | Do not share any personal information (credit card info, bank account, address, etc.) with anyone under any circumstances. Never disclose your personal banking information, including account numbers or passwords. | | | Unsubscribe | | | © 2005 - 2026 Seeking in conjunction with Reflex Media – All rights reserved. W8Tech Cyprus Limited, IRAKLEOUS 2, FLAT/OFFICE 101 2320 NICOSIA, CYPRUS | | I5: 2026-07-30T13:01:41.000Z | J5: Spam | K5: An automated promotional email from the dating platform Seeking, showcasing new profiles in the recipient's geographic area. It also contains standard safety warnings regarding sharing personal information. | L5: No Response Needed | M5: No response is required as this is an automated marketing communication. | N5: No | O5: Processed
A6: EM0006 | B6: 19fc5240ff7770b0 | C6: 19fc5240ff7770b0 | D6: CST0004 | E6: Seeking | F6: alerts@account.seeking.com | G6: Check out the newest members in your area! | H6: 96 Hi Peter, here are some new members in your area! julie 37 &#183; Three Hills Sabrina 31 &#183; Calgary Anita 24 &#183; Calgary Seeking Member 27 &#183; Calgary Seeking Member 33 &#183; Olds Kelsie 35 &#183; Red Deer Search for More | Do not share any personal information (credit card info, bank account, address, etc.) with anyone under any circumstances. Never disclose your personal banking information, including account numbers or passwords. | | | Unsubscribe | | | © 2005 - 2026 Seeking in conjunction with Reflex Media – All rights reserved. W8Tech Cyprus Limited, IRAKLEOUS 2, FLAT/OFFICE 101 2320 NICOSIA, CYPRUS | | I6: 2026-08-03T01:01:42.000Z | J6: Spam | K6: An automated promotional email from the dating platform Seeking, highlighting new members in the recipient's geographic area. | L6: No Response Needed | M6: No response is required for this automated marketing email. | N6: No | O6: Processed
A7: EM0007 | B7: 19fcefbf21d5ecb2 | C7: 19fcefbf21d5ecb2 | D7: CST0005 | E7: Anonymousemail | F7: noreply@anonymousemail.eu | G7: All servers down - FIX ASAP | H7: Powered by Anonymousemail Hi team, All of the servers are currently down. We need someone to look into this problem and fix it immediately. Thanks, Janice | I7: 2026-08-04T22:54:04.000Z | J7: Existing Customer | K7: Janice has reported that all servers are currently down and requested an immediate resolution. | L7: Urgent | M7: Hi Janice, Thank you for bringing this to our attention. Our technical team is immediately investigating this server outage to restore services as quickly as possible. We will keep you updated on our progress. Best regards, Operations Team | N7: Yes | O7: Processed
A8: EM0008 | B8: 19fcf1613efdffdf | C8: 19fcf1613efdffdf | D8: CST0005 | E8: Anonymousemail | F8: noreply@anonymousemail.eu | G8: This is a test | H8: Powered by Anonymousemail Test email but I need it to create a task as well to run a full end-to-end test | I8: 2026-08-04T23:22:37.000Z | J8: Spam | K8: This is a test email sent via Anonymousemail to verify end-to-end task creation functionality. | L8: No Response Needed | M8: Thank you for your email. We have successfully received your test message, and the system is operating as expected. | N8: No | O8: Processed
A9: EM0009 | B9: 19fcf18d32f33ab5 | C9: 19fcf17ea616c2f5 | D9: CST0006 | E9: Darragh Hurley | F9: darraghhurleycanada@gmail.com | G9: New website design | H9: Hi team, We are planning on creating a new website for the cloud team. We are looking for some software engineers and architects to build it for us from scratch. Can we please book in a meeting this week to discuss. Thank you, Darragh | I9: 2026-08-04T23:25:38.000Z | J9: Customer Enquiry | K9: Darragh Hurley is requesting a meeting this week to discuss building a new website for the cloud team from scratch. He is looking to secure software engineers and architects for the project. | L9: Medium | M9: Hi Darragh, Thank you for reaching out. We would be delighted to discuss this project with you and help assemble the right team of software engineers and architects for your new website. Could you please share your availability for a brief meeting this week? Alternatively, let me know if there is a specific day and time that works best for you, and I will send over a calendar invitation. Best regards, [Your Name] [Your Title] | N9: Yes | O9: Processed
A10: EM0010 | B10: demo-msg-0010 | C10: demo-thread-0010 | D10: CST0007 | E10: Sarah Nolan | F10: sarah.nolan@example.com | G10: Request for analytics dashboard | H10: Hi team, could we arrange a call about building a dashboard for our monthly sales reporting? | I10: 46254.385 | J10: Customer enquiry | K10: Sarah wants to discuss a sales reporting dashboard and arrange a call. | L10: Medium | M10: Hi Sarah, thanks for getting in touch. We would be happy to discuss your dashboard requirements. Please send over a few suitable times for a call. | N10: Yes | O10: Processed
A11: EM0011 | B11: demo-msg-0011 | C11: demo-thread-0011 | D11: CST0008 | E11: Michael Chen | F11: michael.chen@example.com | G11: Invoice INV-884 payment confirmation | H11: Hi, we paid invoice INV-884 this morning by bank transfer. Can you confirm receipt? | I11: 46256.472 | J11: Invoice | K11: Michael advises invoice INV-884 has been paid and requests confirmation. | L11: Low | M11: Thanks Michael. We will verify the payment and confirm once it has been matched to the invoice. | N11: Yes | O11: Processed
A12: EM0012 | B12: demo-msg-0012 | C12: demo-thread-0012 | D12: CST0009 | E12: Priya Shah | F12: priya.shah@example.com | G12: Unable to access client portal | H12: I cannot log in to the client portal since this morning. It says my account is locked. | I12: 46259.361 | J12: Existing customer | K12: Priya reports a locked client portal account and needs access restored. | L12: High | M12: Hi Priya, thanks for reporting this. We will check your account status and get back to you shortly. | N12: Yes | O12: Processed
A13: EM0013 | B13: demo-msg-0013 | C13: demo-thread-0013 | D13: CST0014 | E13: Atlas Supplies | F13: orders@atlassupplies.example | G13: Updated hardware price list | H13: Please find our updated workstation and monitor pricing for September attached. | I13: 46260.587 | J13: Supplier | K13: Atlas Supplies sent updated September hardware pricing. | L13: No Response Needed | M13: Thanks for the updated price list. We have received it and will review it for upcoming orders. | N13: No | O13: Processed
A14: EM0014 | B14: demo-msg-0014 | C14: demo-thread-0014 | D14: CST0010 | E14: Tom Gallagher | F14: tom.gallagher@example.com | G14: Website project follow-up | H14: Just checking if you had an update on the proposal for our website redesign. | I14: 46261.674 | J14: Existing customer | K14: Tom is following up on the outstanding website redesign proposal. | L14: Medium | M14: Hi Tom, thanks for following up. We are finalising the proposal and will send an update shortly. | N14: Yes | O14: Processed
A15: EM0015 | B15: demo-msg-0015 | C15: demo-thread-0015 | D15: CST0011 | E15: Emma Clarke | F15: emma.clarke@example.com | G15: Complaint about delayed support response | H15: We reported an outage yesterday and did not receive a response for four hours. This is not acceptable. | I15: 46263.438 | J15: Complaint | K15: Emma complains about a four-hour delay in response to an outage report. | L15: Urgent | M15: Hi Emma, thank you for raising this. We are reviewing the incident and response timeline as a priority and will follow up with you directly. | N15: Yes | O15: Processed
A16: EM0016 | B16: demo-msg-0016 | C16: demo-thread-0016 | D16: CST0015 | E16: Northline Hosting | F16: support@northlinehosting.example | G16: Scheduled maintenance notice | H16: We will perform routine maintenance on Saturday from 01:00 to 03:00 UTC. No action is required. | I16: 46264.75 | J16: Supplier | K16: Northline Hosting advises of scheduled maintenance with no customer action required. | L16: No Response Needed | M16: Thank you for the notice. We have recorded the maintenance window. | N16: No | O16: Error
A17: EM0017 | B17: demo-msg-0017 | C17: demo-thread-0017 | D17: CST0012 | E17: Daniel Ortiz | F17: daniel.ortiz@example.com | G17: Need quote for cloud migration | H17: We are considering moving around 20 virtual machines to Azure and would like an initial estimate. | I17: 46266.375 | J17: Customer enquiry | K17: Daniel requests an estimate for migrating approximately 20 virtual machines to Azure. | L17: High | M17: Hi Daniel, thanks for reaching out. We can help scope the migration and provide an estimate. Could you share your current environment and preferred timeline? | N17: Yes | O17: Processed
A18: EM0018 | B18: demo-msg-0018 | C18: demo-thread-0018 | D18: CST0007 | E18: Sarah Nolan | F18: sarah.nolan@example.com | G18: Re: analytics dashboard requirements | H18: Attached are the KPI definitions we discussed. Can you confirm these are enough to begin? | I18: 46266.559 | J18: Existing customer | K18: Sarah provided KPI definitions for the dashboard project and requests confirmation. | L18: Medium | M18: Hi Sarah, thanks for sending these through. We will review the KPI definitions and confirm whether anything else is needed. | N18: Yes | O18: Processed
A19: EM0019 | B19: demo-msg-0019 | C19: demo-thread-0019 | D19: CST0016 | E19: Olivia Byrne | F19: olivia.byrne@example.com | G19: Invoice total looks incorrect | H19: Our invoice is €450 higher than the amount agreed in the proposal. Could someone review it? | I19: 46267.406 | J19: Invoice | K19: Olivia disputes an invoice that is €450 above the agreed proposal amount. | L19: High | M19: Hi Olivia, thanks for flagging this. We will compare the invoice against the approved proposal and get back to you as soon as possible. | N19: Yes | O19: Processed
A20: EM0020 | B20: demo-msg-0020 | C20: demo-thread-0020 | D20: CST0010 | E20: Tom Gallagher | F20: tom.gallagher@example.com | G20: Re: website proposal approved | H20: The proposal looks good and is approved. What are the next steps? | I20: 46267.632 | J20: Existing customer | K20: Tom confirms approval of the website proposal and asks for next steps. | L20: Medium | M20: Great, thank you Tom. We will prepare the project kickoff details and proposed start date and send them over shortly. | N20: Yes | O20: Processed
A21: EM0021 | B21: demo-msg-0021 | C21: demo-thread-0021 | D21: CST0013 | E21: Rachel Kim | F21: rachel.kim@example.com | G21: Security assessment enquiry | H21: Do you provide security assessments for Microsoft 365 environments? We have around 80 users. | I21: 46267.694 | J21: Customer enquiry | K21: Rachel asks about a Microsoft 365 security assessment for an 80-user organisation. | L21: Medium | M21: Hi Rachel, yes, we can help assess Microsoft 365 security. We would be happy to arrange a discovery call to understand your environment and priorities. | N21: Yes | O21: Processed
... A31: EM0031 | B31: demo-msg-0031 | C31: demo-thread-0031 | D31: CST0017 | E31: James Doyle | F31: james.doyle@example.com | G31: Automation discovery meeting | H31: Tuesday afternoon works for us. Please send a calendar invite. | I31: 46271.434 | J31: Customer enquiry | K31: James confirms Tuesday afternoon for an automation discovery meeting. | L31: Medium | M31: Perfect, thanks James. We will send a calendar invitation for Tuesday afternoon. | N31: Yes | O31: Processed
A32: EM0032 | B32: demo-msg-0032 | C32: demo-thread-0032 | E32: Prize Centre | F32: winner@fakeprize.example | G32: You have won a €5,000 gift card | H32: Click this link now to claim your reward before midnight. | I32: 46271.458 | J32: Spam | K32: Unsolicited prize message with suspicious call to action. | L32: No Response Needed | N32: No | O32: Processed
A33: EM0033 | B33: demo-msg-0033 | C33: demo-thread-0033 | E33: Crypto Growth | F33: offers@cryptogrowth.example | G33: Double your investment this week | H33: Guaranteed returns with our exclusive crypto trading system. Sign up today. | I33: 46271.49 | J33: Spam | K33: Unsolicited promotional email promising unrealistic investment returns. | L33: No Response Needed | N33: No | O33: Processed

Sheet Activity Log
A1: Timestamp | B1: Action Type | C1: Entity ID | D1: Entity Type | E1: Description | F1: AI Response | G1: Result | H1: Error Message
A2: 2026-08-04T22:54:36.094Z | B2: Received Email | D2: Email | E2: Incoming Email from
A3: 2026-08-04T22:54:37.116Z | B3: New customer | C3: CST0004 | D3: Customer | E3: Created new customer Seeking
A4: 2026-08-04T22:54:37.542Z | B4: Received Email | D4: Email | E4: Incoming Email from
A5: 2026-08-04T22:54:38.254Z | B5: Received Email | D5: Email | E5: Incoming Email from
A6: 2026-08-04T22:54:39.064Z | B6: Received Email | D6: Email | E6: Incoming Email from
A7: 2026-08-04T22:54:39.503Z | B7: New customer | C7: CST0005 | D7: Customer | E7: Created new customer Anonymousemail
A8: 2026-08-04T23:07:09.304Z | B8: AI Summary | C8: EM0004 | D8: Email | E8: Email summarized by AI | F8: This is an automated promotional email from Seeking.com showcasing new members in the recipient's area.
A9: 2026-08-04T23:07:15.222Z | B9: AI Summary | C9: EM0005 | D9: Email | E9: Email summarized by AI | F9: An automated promotional email from the dating platform Seeking, showcasing new profiles in the recipient's geographic area. It also contains standard safety warnings regarding sharing personal information.
A10: 2026-08-04T23:07:22.370Z | B10: AI Summary | C10: EM0006 | D10: Email | E10: Email summarized by AI | F10: An automated promotional email from the dating platform Seeking, highlighting new members in the recipient's geographic area.
A11: 2026-08-04T23:07:39.616Z | B11: AI Summary | C11: EM0007 | D11: Email | E11: Email summarized by AI | F11: Janice has reported that all servers are currently down and requested an immediate resolution.
A12: 2026-08-04T23:07:39.955Z | B12: Task Created | C12: TSK00017 | D12: Task | E12: New Task Created for EmailEM0007
A13: 2026-08-04T23:07:40.590Z | B13: Employee Assigned | C13: EP003 | D13: Employee | E13: David Trainer has been assigned TSK00017
A14: 2026-08-04T23:23:00.225Z | B14: Received Email | C14: EM0008 | D14: Email | E14: Incoming Email from Anonymousemail
A15: 2026-08-04T23:24:00.948Z | B15: AI Summary | C15: EM0008 | D15: Email | E15: Email summarized by AI | F15: This is a test email sent via Anonymousemail to verify end-to-end task creation functionality.
A16: 2026-08-04T23:25:57.113Z | B16: Received Email | C16: EM0009 | D16: Email | E16: Incoming Email from Darragh Hurley
A17: 2026-08-04T23:25:57.590Z | B17: New customer | C17: CST0006 | D17: Customer | E17: Created new customer Darragh Hurley
A18: 2026-08-04T23:27:22.083Z | B18: AI Summary | C18: EM0009 | D18: Email | E18: Email summarized by AI | F18: Darragh Hurley is requesting a meeting this week to discuss building a new website for the cloud team from scratch. He is looking to secure software engineers and architects for the project.
A19: 2026-08-04T23:27:23.383Z | B19: Task Created | C19: TSK00018 | D19: Task | E19: New Task Created for EmailEM0009
A20: 2026-08-04T23:27:28.494Z | B20: Employee Assigned | C20: EP003 | D20: Employee | E20: David Trainer has been assigned TSK00018
A21: 2026-08-05T18:48:02.575Z | B21: Task Completed | C21: TSK00016 | D21: Task | E21: The sender is inquiring about how to RSVP for an upcoming event on August 3rd because the invitation email did not include an RSVP option. | G21: Cancelled
A22: 2026-08-05T18:48:03.629Z | B22: Task Completed | C22: TSK00017 | D22: Task | E22: Janice has reported that all servers are currently down and requested an immediate resolution. | G22: Completed

Sheet Tasks
A1: Task ID | B1: Email ID | C1: Customer ID | D1: Assigned Employee ID | E1: Description | F1: Priority | G1: Created Date | H1: Due Date | I1: Status | J1: Completed Date | K1: Notes
A2: TSK00015 | B2: EM0002 | C2: CST0002 | D2: EP002 | E2: Darragh Hurley has requested to reschedule the meeting set for Monday, July 27th, due to illness. He has asked to move the appointment to a later date in the same week. | F2: Medium | G2: 46235 | I2: Assigned
A3: TSK00016 | B3: EM0003 | C3: CST0003 | D3: EP001 | E3: The sender is inquiring about how to RSVP for an upcoming event on August 3rd because the invitation email did not include an RSVP option. | F3: Medium | G3: 46235 | I3: Cancelled | J3: 46239
A4: TSK00017 | B4: EM0007 | C4: CST0005 | D4: EP003 | E4: Janice has reported that all servers are currently down and requested an immediate resolution. | F4: Urgent | G4: 46238 | I4: Completed | J4: 46239
A5: TSK00018 | B5: EM0009 | C5: CST0006 | D5: EP003 | E5: Darragh Hurley is requesting a meeting this week to discuss building a new website for the cloud team from scratch. He is looking to secure software engineers and architects for the project. | F5: Medium | G5: 46238 | I5: Assigned
A6: TSK00019 | B6: EM0010 | C6: CST0007 | D6: EP004 | E6: Arrange discovery call for Sarah Nolan's sales analytics dashboard request. | F6: Medium | G6: 46254 | H6: 46256 | I6: Completed | J6: 46255 | K6: Discovery call booked.
A7: TSK00020 | B7: EM0011 | C7: CST0008 | D7: EP002 | E7: Verify payment for invoice INV-884 and confirm receipt to Michael Chen. | F7: Low | G7: 46256 | H7: 46258 | I7: Completed | J7: 46256 | K7: Payment matched.
A8: TSK00021 | B8: EM0012 | C8: CST0009 | D8: EP001 | E8: Investigate Priya Shah's locked client portal account and restore access. | F8: High | G8: 46259 | H8: 46259 | I8: Completed | J8: 46259 | K8: Account unlocked.
A9: TSK00022 | B9: EM0014 | C9: CST0010 | D9: EP004 | E9: Send Tom Gallagher an update on the website redesign proposal. | F9: Medium | G9: 46261 | H9: 46262 | I9: Completed | J9: 46262 | K9: Proposal sent.
A10: TSK00023 | B10: EM0015 | C10: CST0011 | D10: EP001 | E10: Review delayed outage support response and prepare incident explanation for Emma Clarke. | F10: Urgent | G10: 46263 | H10: 46263 | I10: Completed | J10: 46263 | K10: Incident timeline reviewed.
A11: TSK00024 | B11: EM0017 | C11: CST0012 | D11: EP003 | E11: Prepare initial Azure migration estimate for Daniel Ortiz. | F11: High | G11: 46266 | H11: 46268 | I11: Assigned | K11: Waiting on technical environment details.
A12: TSK00025 | B12: EM0018 | C12: CST0007 | D12: EP004 | E12: Review KPI definitions supplied by Sarah Nolan and confirm whether requirements are complete. | F12: Medium | G12: 46266 | H12: 46267 | I12: Assigned
A13: TSK00026 | B13: EM0019 | C13: CST0016 | D13: EP002 | E13: Compare Olivia Byrne's disputed invoice against the approved proposal and correct if required. | F13: High | G13: 46267 | H13: 46267 | I13: Completed | J13: 46268 | K13: Invoice corrected.
A14: TSK00027 | B14: EM0020 | C14: CST0010 | D14: EP004 | E14: Prepare website project kickoff steps and proposed start date for Tom Gallagher. | F14: Medium | G14: 46267 | H14: 46270 | I14: Assigned
A15: TSK00028 | B15: EM0021 | C15: CST0013 | D15: EP001 | E15: Arrange discovery call for Rachel Kim's Microsoft 365 security assessment enquiry. | F15: Medium | G15: 46267 | H15: 46270 | I15: Assigned
A16: TSK00029 | B16: EM0023 | C16: CST0011 | D16: EP001 | E16: Schedule incident review meeting with Emma Clarke and prepare escalation process summary. | F16: High | G16: 46268 | H16: 46271 | I16: Waiting | K16: Meeting agenda drafted.
A17: TSK00030 | B17: EM0024 | C17: CST0017 | D17: EP004 | E17: Map James Doyle's manual form approval process and prepare automation discovery questions. | F17: Medium | G17: 46269 | H17: 46272 | I17: In Progress
A18: TSK00031 | B18: EM0025 | C18: CST0014 | D18: EP002 | E18: Update delivery tracking for delayed supplier order 4457 and assess project impact. | F18: Low | G18: 46269 | H18: 46270 | I18: Completed | J18: 46270 | K18: Delivery date updated.
A19: TSK00032 | B19: EM0026 | C19: CST0008 | D19: EP002 | E19: Verify INV-884 status and stop duplicate payment reminders for Michael Chen. | F19: Medium | G19: 46270 | H19: 46271 | I19: Assigned
A20: TSK00033 | B20: EM0028 | C20: CST0018 | D20: EP001 | E20: Investigate finance shared drive outage and restore access as an urgent incident. | F20: Urgent | G20: 46270 | H20: 46270 | I20: In Progress | K20: Incident escalated.
A21: TSK00034 | B21: EM0029 | C21: CST0012 | D21: EP003 | E21: Schedule technical discovery session for Daniel Ortiz's Azure migration. | F21: Medium | G21: 46270 | H21: 46273 | I21: Assigned
A22: TSK00035 | B22: EM0031 | C22: CST0017 | D22: EP004 | E22: Send Tuesday afternoon calendar invitation to James Doyle for automation discovery meeting. | F22: Medium | G22: 46271 | H22: 46271 | I22: Completed | J22: 46271 | K22: Invite sent.

Sheet Customers
A1: Customer ID | B1: Customer Name | C1: Customer Email | D1: First Contact Date | E1: Last Contact Date | F1: Status | G1: Total Emails
A2: CST0002 | B2: Darragh Hurley | C2: dazmanchelsea@gmail.com | D2: 2026-07-25T19:34:03.000Z | E2: 2026-07-25T19:34:03.000Z | F2: Active
A3: CST0003 | B3: Darragh Hurley | C3: darragh.hurley23@gmail.com | D3: 2026-07-25T19:40:56.000Z | E3: 2026-07-25T19:40:56.000Z | F3: Active
A4: CST0004 | B4: Seeking | C4: alerts@account.seeking.com | D4: 2026-07-27T01:01:42.000Z | E4: 2026-07-27T01:01:42.000Z | F4: Active
A5: CST0005 | B5: Anonymousemail | C5: noreply@anonymousemail.eu | D5: 2026-08-04T22:54:04.000Z | E5: 2026-08-04T22:54:04.000Z | F5: Active
A6: CST0006 | B6: Darragh Hurley | C6: darraghhurleycanada@gmail.com | D6: 2026-08-04T23:25:38.000Z | E6: 2026-08-04T23:25:38.000Z | F6: Active
A7: CST0007 | B7: Sarah Nolan | C7: sarah.nolan@example.com | D7: 46254 | E7: 46269 | F7: Active | G7: 3
A8: CST0008 | B8: Michael Chen | C8: michael.chen@example.com | D8: 46256 | E8: 46270 | F8: Active | G8: 3
A9: CST0009 | B9: Priya Shah | C9: priya.shah@example.com | D9: 46259 | E9: 46268 | F9: Active | G9: 2
A10: CST0010 | B10: Tom Gallagher | C10: tom.gallagher@example.com | D10: 46261 | E10: 46267 | F10: Active | G10: 2
A11: CST0011 | B11: Emma Clarke | C11: emma.clarke@example.com | D11: 46263 | E11: 46271 | F11: Active | G11: 3
A12: CST0012 | B12: Daniel Ortiz | C12: daniel.ortiz@example.com | D12: 46266 | E12: 46271 | F12: Active | G12: 2
A13: CST0013 | B13: Rachel Kim | C13: rachel.kim@example.com | D13: 46267 | E13: 46270 | F13: Active | G13: 2
A14: CST0014 | B14: Atlas Supplies | C14: orders@atlassupplies.example | D14: 46252 | E14: 46269 | F14: Supplier | G14: 2
A15: CST0015 | B15: Northline Hosting | C15: support@northlinehosting.example | D15: 46264 | E15: 46270 | F15: Supplier | G15: 2
A16: CST0016 | B16: Olivia Byrne | C16: olivia.byrne@example.com | D16: 46268 | E16: 46271 | F16: Active | G16: 2
A17: CST0017 | B17: James Doyle | C17: james.doyle@example.com | D17: 46269 | E17: 46271 | F17: Active | G17: 2
A18: CST0018 | B18: Nora Walsh | C18: nora.walsh@example.com | D18: 46270 | E18: 46271 | F18: Active | G18: 1

Sheet Employees
A1: Employee ID | B1: Employee Name | C1: Email | D1: Phone | E1: Status | F1: Role | G1: Current Task Count | H1: Last Assigned Date | I1: Assignment Rank
A2: EP001 | B2: Jake Marshall | C2: jmarshall@gmail.com | D2: 8253651111 | E2: Busy | F2: Software Developer | G2: 3 | H2: 46270 | I2: 000003-20260905
A3: EP002 | B3: Donna Rourke | C3: drourke@gmail.com | D3: 8254764765 | E3: Available | F3: Head of Finance | G3: 1 | H3: 46270 | I3: 000001-20260905
A4: EP003 | B4: David Trainer | C4: dtrainer@gmail.com | D4: 8251234325 | E4: Available | F4: Accountant | G4: 2 | H4: 46270 | I4: 000002-20260905
A5: EP004 | B5: Harry Lewis | C5: hlewis@gmail.com | D5: 8250009090 | E5: Busy | F5: Cloud Consultant | G5: 3 | H5: 46271 | I5: 000003-20260906

Sheet Settings
A1: Email Categories | C1: Email Priority | E1: Email Processing Status | G1: Task Status | I1: Employee Status
A2: Customer enquiry | C2: Urgent | E2: New | G2: New | I2: Available
A3: Existing customer | C3: High | E3: Processing | G3: Assigned | I3: Busy
A4: Invoice | C4: Medium | E4: Processed | G4: In Progress | I4: Away
A5: Supplier | C5: Low | E5: Error | G5: Waiting | I5: Inactive
A6: Complaint | C6: No response needed | E6: No Action Required | G6: Completed
A7: Spam | G7: Cancelled
